transformers_crf/__init__.py
transformers_crf/bert_crf.py
transformers_crf/bert_crf_modern.py
transformers_crf/bert_crf_no_modern.py
transformers_crf/crf.py
transformers_crf/data_collator.py
transformers_crf/export_onnx.py
transformers_crf/ort_model.py
transformers_crf/tokenizer.py
transformers_crf/trainer.py
transformers_crf/transformer_embedder.py
transformers_crf/util.py
transformers_crf/version.py
transformers_crf-0.3.2.dist-info/METADATA
transformers_crf-0.3.2.dist-info/WHEEL
transformers_crf-0.3.2.dist-info/top_level.txt
transformers_crf-0.3.2.dist-info/zip-safe
transformers_crf-0.3.2.dist-info/RECORD
