Metadata-Version: 2.4
Name: transformers_crf
Version: 0.3.2
Summary: Transformers CRF: CRF Token Classification for Transformers
Home-page: https://bitbucket.org/avisourgente/transformers_crf
Author: Eduardo Garcia - Datalawyer
License: Apache License 2.0
Platform: any
Requires-Python: >=3.7.0
Requires-Dist: transformers==4.56.1
Requires-Dist: datasets>=1.8.0
Requires-Dist: onnx
Requires-Dist: onnxruntime
Requires-Dist: optimum
Requires-Dist: seqeval
Requires-Dist: evaluate
Requires-Dist: accelerate
Requires-Dist: wandb
Dynamic: author
Dynamic: description
Dynamic: description-content-type
Dynamic: home-page
Dynamic: license
Dynamic: platform
Dynamic: requires-dist
Dynamic: requires-python
Dynamic: summary
